medpc2excel/__init__.py
medpc2excel/__main__.py
medpc2excel/gui.py
medpc2excel/medpc_read.py
medpc2excel-3.10.0.dist-info/LICENSE
medpc2excel-3.10.0.dist-info/METADATA
medpc2excel-3.10.0.dist-info/WHEEL
medpc2excel-3.10.0.dist-info/top_level.txt
medpc2excel-3.10.0.dist-info/RECORD
