Metadata-Version: 2.1
Name: medpc2excel
Version: 3.10.0
Summary: export medpc data to excel file and generate user defined variables
Home-page: https://github.com/cyf203/medpc2excel
Author: Yifeng Cheng
Author-email: cyfhopkins@gmail.com
License: MIT
Platform: UNKNOWN
Classifier: Programming Language :: Python :: 3
Classifier: License :: OSI Approved :: MIT License
Classifier: Operating System :: OS Independent
Requires-Dist: numpy
Requires-Dist: pandas
Requires-Dist: dill
